[
  {
    "inputs": [
      {
        "internalType": "contract BufferBinaryPool",
        "name": "_pool",
        "type": "address"
      }
    ],
    "stateMutability": "nonpayable",
    "type": "constructor"
  },
  {
    "anonymous": false,
    "inputs": [
      {
        "indexed": true,
        "internalType": "address",
        "name": "previousOwner",
        "type": "address"
      },
      {
        "indexed": true,
        "internalType": "address",
        "name": "newOwner",
        "type": "address"
      }
    ],
    "name": "OwnershipTransferred",
    "type": "event"
  },
  {
    "anonymous": false,
    "inputs": [
      {
        "indexed": false,
        "internalType": "address",
        "name": "_boosterContract",
        "type": "address"
      }
    ],
    "name": "UpdateBoosterContract",
    "type": "event"
  },
  {
    "anonymous": false,
    "inputs": [
      {
        "indexed": false,
        "internalType": "address",
        "name": "value",
        "type": "address"
      }
    ],
    "name": "UpdateCreationWindowContract",
    "type": "event"
  },
  {
    "anonymous": false,
    "inputs": [
      {
        "indexed": false,
        "internalType": "bool",
        "name": "isAllowed",
        "type": "bool"
      }
    ],
    "name": "UpdateEarlyClose",
    "type": "event"
  },
  {
    "anonymous": false,
    "inputs": [
      {
        "indexed": false,
        "internalType": "uint32",
        "name": "earlyCloseThreshold",
        "type": "uint32"
      }
    ],
    "name": "UpdateEarlyCloseThreshold",
    "type": "event"
  },
  {
    "anonymous": false,
    "inputs": [
      {
        "indexed": false,
        "internalType": "uint256",
        "name": "_iv",
        "type": "uint256"
      }
    ],
    "name": "UpdateIV",
    "type": "event"
  },
  {
    "anonymous": false,
    "inputs": [
      {
        "indexed": false,
        "internalType": "address",
        "name": "_marketOIConfigContract",
        "type": "address"
      }
    ],
    "name": "UpdateMarketOIConfigContract",
    "type": "event"
  },
  {
    "anonymous": false,
    "inputs": [
      {
        "indexed": false,
        "internalType": "uint32",
        "name": "value",
        "type": "uint32"
      }
    ],
    "name": "UpdateMaxPeriod",
    "type": "event"
  },
  {
    "anonymous": false,
    "inputs": [
      {
        "indexed": false,
        "internalType": "uint256",
        "name": "value",
        "type": "uint256"
      }
    ],
    "name": "UpdateMinFee",
    "type": "event"
  },
  {
    "anonymous": false,
    "inputs": [
      {
        "indexed": false,
        "internalType": "uint32",
        "name": "value",
        "type": "uint32"
      }
    ],
    "name": "UpdateMinPeriod",
    "type": "event"
  },
  {
    "anonymous": false,
    "inputs": [
      {
        "indexed": false,
        "internalType": "address",
        "name": "value",
        "type": "address"
      }
    ],
    "name": "UpdateOptionStorageContract",
    "type": "event"
  },
  {
    "anonymous": false,
    "inputs": [
      {
        "indexed": false,
        "internalType": "uint256",
        "name": "_platformFee",
        "type": "uint256"
      }
    ],
    "name": "UpdatePlatformFee",
    "type": "event"
  },
  {
    "anonymous": false,
    "inputs": [
      {
        "indexed": false,
        "internalType": "address",
        "name": "_poolOIConfigContract",
        "type": "address"
      }
    ],
    "name": "UpdatePoolOIConfigContract",
    "type": "event"
  },
  {
    "anonymous": false,
    "inputs": [
      {
        "indexed": false,
        "internalType": "address",
        "name": "_poolOIStorageContract",
        "type": "address"
      }
    ],
    "name": "UpdatePoolOIStorageContract",
    "type": "event"
  },
  {
    "anonymous": false,
    "inputs": [
      {
        "indexed": false,
        "internalType": "address",
        "name": "value",
        "type": "address"
      }
    ],
    "name": "UpdateSettlementFeeDisbursalContract",
    "type": "event"
  },
  {
    "anonymous": false,
    "inputs": [
      {
        "indexed": false,
        "internalType": "address",
        "name": "value",
        "type": "address"
      }
    ],
    "name": "UpdatetraderNFTContract",
    "type": "event"
  },
  {
    "inputs": [],
    "name": "boosterContract",
    "outputs": [{ "internalType": "address", "name": "", "type": "address" }],
    "stateMutability": "view",
    "type": "function"
  },
  {
    "inputs": [],
    "name": "creationWindowContract",
    "outputs": [{ "internalType": "address", "name": "", "type": "address" }],
    "stateMutability": "view",
    "type": "function"
  },
  {
    "inputs": [],
    "name": "earlyCloseThreshold",
    "outputs": [{ "internalType": "uint32", "name": "", "type": "uint32" }],
    "stateMutability": "view",
    "type": "function"
  },
  {
    "inputs": [],
    "name": "isEarlyCloseAllowed",
    "outputs": [{ "internalType": "bool", "name": "", "type": "bool" }],
    "stateMutability": "view",
    "type": "function"
  },
  {
    "inputs": [],
    "name": "iv",
    "outputs": [{ "internalType": "uint256", "name": "", "type": "uint256" }],
    "stateMutability": "view",
    "type": "function"
  },
  {
    "inputs": [],
    "name": "marketOIConfigContract",
    "outputs": [{ "internalType": "address", "name": "", "type": "address" }],
    "stateMutability": "view",
    "type": "function"
  },
  {
    "inputs": [],
    "name": "maxPeriod",
    "outputs": [{ "internalType": "uint32", "name": "", "type": "uint32" }],
    "stateMutability": "view",
    "type": "function"
  },
  {
    "inputs": [],
    "name": "minFee",
    "outputs": [{ "internalType": "uint256", "name": "", "type": "uint256" }],
    "stateMutability": "view",
    "type": "function"
  },
  {
    "inputs": [],
    "name": "minPeriod",
    "outputs": [{ "internalType": "uint32", "name": "", "type": "uint32" }],
    "stateMutability": "view",
    "type": "function"
  },
  {
    "inputs": [],
    "name": "optionStorageContract",
    "outputs": [{ "internalType": "address", "name": "", "type": "address" }],
    "stateMutability": "view",
    "type": "function"
  },
  {
    "inputs": [],
    "name": "owner",
    "outputs": [{ "internalType": "address", "name": "", "type": "address" }],
    "stateMutability": "view",
    "type": "function"
  },
  {
    "inputs": [],
    "name": "platformFee",
    "outputs": [{ "internalType": "uint256", "name": "", "type": "uint256" }],
    "stateMutability": "view",
    "type": "function"
  },
  {
    "inputs": [],
    "name": "pool",
    "outputs": [
      {
        "internalType": "contract BufferBinaryPool",
        "name": "",
        "type": "address"
      }
    ],
    "stateMutability": "view",
    "type": "function"
  },
  {
    "inputs": [],
    "name": "poolOIConfigContract",
    "outputs": [{ "internalType": "address", "name": "", "type": "address" }],
    "stateMutability": "view",
    "type": "function"
  },
  {
    "inputs": [],
    "name": "poolOIStorageContract",
    "outputs": [{ "internalType": "address", "name": "", "type": "address" }],
    "stateMutability": "view",
    "type": "function"
  },
  {
    "inputs": [],
    "name": "renounceOwnership",
    "outputs": [],
    "stateMutability": "nonpayable",
    "type": "function"
  },
  {
    "inputs": [
      {
        "internalType": "address",
        "name": "_boosterContract",
        "type": "address"
      }
    ],
    "name": "setBoosterContract",
    "outputs": [],
    "stateMutability": "nonpayable",
    "type": "function"
  },
  {
    "inputs": [
      {
        "internalType": "address",
        "name": "_creationWindowContract",
        "type": "address"
      }
    ],
    "name": "setCreationWindowContract",
    "outputs": [],
    "stateMutability": "nonpayable",
    "type": "function"
  },
  {
    "inputs": [
      {
        "internalType": "uint32",
        "name": "_earlyCloseThreshold",
        "type": "uint32"
      }
    ],
    "name": "setEarlyCloseThreshold",
    "outputs": [],
    "stateMutability": "nonpayable",
    "type": "function"
  },
  {
    "inputs": [{ "internalType": "uint256", "name": "_iv", "type": "uint256" }],
    "name": "setIV",
    "outputs": [],
    "stateMutability": "nonpayable",
    "type": "function"
  },
  {
    "inputs": [
      {
        "internalType": "address",
        "name": "_marketOIConfigContract",
        "type": "address"
      }
    ],
    "name": "setMarketOIConfigContract",
    "outputs": [],
    "stateMutability": "nonpayable",
    "type": "function"
  },
  {
    "inputs": [
      { "internalType": "uint32", "name": "_maxPeriod", "type": "uint32" }
    ],
    "name": "setMaxPeriod",
    "outputs": [],
    "stateMutability": "nonpayable",
    "type": "function"
  },
  {
    "inputs": [
      { "internalType": "uint256", "name": "_minFee", "type": "uint256" }
    ],
    "name": "setMinFee",
    "outputs": [],
    "stateMutability": "nonpayable",
    "type": "function"
  },
  {
    "inputs": [
      { "internalType": "uint32", "name": "_minPeriod", "type": "uint32" }
    ],
    "name": "setMinPeriod",
    "outputs": [],
    "stateMutability": "nonpayable",
    "type": "function"
  },
  {
    "inputs": [
      {
        "internalType": "address",
        "name": "_optionStorageContract",
        "type": "address"
      }
    ],
    "name": "setOptionStorageContract",
    "outputs": [],
    "stateMutability": "nonpayable",
    "type": "function"
  },
  {
    "inputs": [
      { "internalType": "uint256", "name": "_platformFee", "type": "uint256" }
    ],
    "name": "setPlatformFee",
    "outputs": [],
    "stateMutability": "nonpayable",
    "type": "function"
  },
  {
    "inputs": [
      {
        "internalType": "address",
        "name": "_poolOIConfigContract",
        "type": "address"
      }
    ],
    "name": "setPoolOIConfigContract",
    "outputs": [],
    "stateMutability": "nonpayable",
    "type": "function"
  },
  {
    "inputs": [
      {
        "internalType": "address",
        "name": "_poolOIStorageContract",
        "type": "address"
      }
    ],
    "name": "setPoolOIStorageContract",
    "outputs": [],
    "stateMutability": "nonpayable",
    "type": "function"
  },
  {
    "inputs": [
      {
        "internalType": "address",
        "name": "_settlementFeeDisbursalContract",
        "type": "address"
      }
    ],
    "name": "setSettlementFeeDisbursalContract",
    "outputs": [],
    "stateMutability": "nonpayable",
    "type": "function"
  },
  {
    "inputs": [],
    "name": "settlementFeeDisbursalContract",
    "outputs": [{ "internalType": "address", "name": "", "type": "address" }],
    "stateMutability": "view",
    "type": "function"
  },
  {
    "inputs": [],
    "name": "toggleEarlyClose",
    "outputs": [],
    "stateMutability": "nonpayable",
    "type": "function"
  },
  {
    "inputs": [
      { "internalType": "address", "name": "newOwner", "type": "address" }
    ],
    "name": "transferOwnership",
    "outputs": [],
    "stateMutability": "nonpayable",
    "type": "function"
  }
]
